brian_dash/__init__.py
brian_dash/input_factory.py
brian_dash/utility.py
brian_dash/models/HH.py
brian_dash/models/__init__.py
brian_dash-0.1.dist-info/LICENSE
brian_dash-0.1.dist-info/METADATA
brian_dash-0.1.dist-info/WHEEL
brian_dash-0.1.dist-info/top_level.txt
brian_dash-0.1.dist-info/RECORD
